Metadata-Version: 2.4
Name: SQLAlchemy-Continuum
Version: 1.5.2
Summary: Versioning and auditing extension for SQLAlchemy.
Author: Mark Steward, Jose Soto
Author-email: Konsta Vesterinen <konsta@fastmonkeys.com>
License-Expression: BSD-3-Clause
Project-URL: Homepage, https://github.com/kvesteri/sqlalchemy-continuum
Classifier: Environment :: Web Environment
Classifier: Intended Audience :: Developers
Classifier: Operating System :: OS Independent
Classifier: Programming Language :: Python
Classifier: Programming Language :: Python :: 3
Classifier: Programming Language :: Python :: 3.9
Classifier: Programming Language :: Python :: 3.10
Classifier: Programming Language :: Python :: 3.11
Classifier: Programming Language :: Python :: 3.12
Classifier: Programming Language :: Python :: 3.13
Classifier: Programming Language :: Python :: 3.14
Classifier: Topic :: Internet :: WWW/HTTP :: Dynamic Content
Classifier: Topic :: Software Development :: Libraries :: Python Modules
Requires-Python: >=3.9
License-File: LICENSE
Requires-Dist: SQLAlchemy<2.1,>=1.4.53
Provides-Extra: test
Requires-Dist: pytest>=2.3.5; extra == "test"
Requires-Dist: psycopg2>=2.4.6; extra == "test"
Requires-Dist: PyMySQL>=0.8.0; extra == "test"
Requires-Dist: Flask>=0.9; extra == "test"
Requires-Dist: Flask-Login>=0.2.9; extra == "test"
Requires-Dist: Flask-SQLAlchemy>=1.0; extra == "test"
Requires-Dist: packaging; extra == "test"
Provides-Extra: flask
Requires-Dist: Flask>=0.9; extra == "flask"
Provides-Extra: flask-login
Requires-Dist: Flask-Login>=0.2.9; extra == "flask-login"
Provides-Extra: flask-sqlalchemy
Requires-Dist: Flask-SQLAlchemy>=1.0; extra == "flask-sqlalchemy"
Provides-Extra: dev
Requires-Dist: ruff>=0.1.0; extra == "dev"
Requires-Dist: tox>=4.0.0; extra == "dev"
Requires-Dist: pre-commit>=3.0.0; extra == "dev"
Provides-Extra: docs
Requires-Dist: sphinx>=4.0.0; extra == "docs"
Requires-Dist: furo>=2021.11.0; extra == "docs"
Dynamic: license-file
